mockalot/__init__.py
mockalot/config.py
mockalot/exceptions.py
mockalot/generators/__init__.py
mockalot/generators/_base.py
mockalot/generators/address.py
mockalot/generators/general.py
mockalot/generators/internet.py
mockalot/generators/number.py
mockalot/generators/person.py
mockalot/generators/time.py
mockalot/log.py
mockalot/writers/__init__.py
mockalot/writers/_base.py
mockalot/writers/binary_files.py
mockalot/writers/in_memory.py
mockalot/writers/text_files.py
mockalot-0.3.1.dist-info/LICENSE
mockalot-0.3.1.dist-info/METADATA
mockalot-0.3.1.dist-info/WHEEL
mockalot-0.3.1.dist-info/RECORD
