Metadata-Version: 2.1
Name: mockalot
Version: 0.3.1
Summary: Mockup data generator library.
Home-page: https://github.com/flavsdotpy/mockalot
License: MIT
Author: Flávio Teixeira
Author-email: flavio.mtps@gmail.com
Requires-Python: >=3.10,<4.0
Classifier: License :: OSI Approved :: MIT License
Classifier: Programming Language :: Python :: 3
Classifier: Programming Language :: Python :: 3.10
Classifier: Programming Language :: Python :: 3.11
Classifier: Programming Language :: Python :: 3.12
Provides-Extra: pandas
Provides-Extra: parquet
Provides-Extra: pyspark
Requires-Dist: Faker (>=24.4.0,<25.0.0)
Requires-Dist: pandas (>=2.2.1,<3.0.0) ; extra == "pandas"
Requires-Dist: pyarrow (>=15.0.2,<16.0.0) ; extra == "parquet"
Requires-Dist: pyspark (>=3.5.1,<4.0.0) ; extra == "pyspark"
Project-URL: Documentation, https://flavsdotpy.github.io/mockalot/
Project-URL: Repository, https://github.com/flavsdotpy/mockalot
